{"metadata": {"dbt_schema_version": "https://schemas.getdbt.com/dbt/run-results/v3.json", "dbt_version": "0.21.1", "generated_at": "2022-05-23T20:26:51.853521Z", "invocation_id": "4830ad12-aca2-4238-b4a0-44119954c640", "env": {}}, "results": [{"status": "success", "timing": [{"name": "compile", "started_at": "2022-05-23T20:26:51.691328Z", "completed_at": "2022-05-23T20:26:51.700648Z"}, {"name": "execute", "started_at": "2022-05-23T20:26:51.701146Z", "completed_at": "2022-05-23T20:26:51.701173Z"}], "thread_id": "Thread-1", "execution_time": 0.011317014694213867, "adapter_response": {}, "message": null, "failures": null, "unique_id": "model.basedosdados.br_ibge_inpc_mes_brasil"}, {"status": "success", "timing": [{"name": "compile", "started_at": "2022-05-23T20:26:51.696909Z", "completed_at": "2022-05-23T20:26:51.705421Z"}, {"name": "execute", "started_at": "2022-05-23T20:26:51.705809Z", "completed_at": "2022-05-23T20:26:51.705819Z"}], "thread_id": "Thread-2", "execution_time": 0.010162830352783203, "adapter_response": {}, "message": null, "failures": null, "unique_id": "model.basedosdados.br_ibge_inpc_mes_categoria_brasil"}, {"status": "success", "timing": [{"name": "compile", "started_at": "2022-05-23T20:26:51.702615Z", "completed_at": "2022-05-23T20:26:51.709336Z"}, {"name": "execute", "started_at": "2022-05-23T20:26:51.709646Z", "completed_at": "2022-05-23T20:26:51.709655Z"}], "thread_id": "Thread-1", "execution_time": 0.007843494415283203, "adapter_response": {}, "message": null, "failures": null, "unique_id": "model.basedosdados.dia"}, {"status": "success", "timing": [{"name": "compile", "started_at": "2022-05-23T20:26:51.707545Z", "completed_at": "2022-05-23T20:26:51.714041Z"}, {"name": "execute", "started_at": "2022-05-23T20:26:51.714432Z", "completed_at": "2022-05-23T20:26:51.714441Z"}], "thread_id": "Thread-2", "execution_time": 0.008020877838134766, "adapter_response": {}, "message": null, "failures": null, "unique_id": "model.basedosdados.mes"}, {"status": "success", "timing": [{"name": "compile", "started_at": "2022-05-23T20:26:51.716947Z", "completed_at": "2022-05-23T20:26:51.720314Z"}, {"name": "execute", "started_at": "2022-05-23T20:26:51.721442Z", "completed_at": "2022-05-23T20:26:51.721454Z"}], "thread_id": "Thread-2", "execution_time": 0.0061893463134765625, "adapter_response": {}, "message": null, "failures": null, "unique_id": "model.basedosdados.mes_brasil_ipca15"}, {"status": "success", "timing": [{"name": "compile", "started_at": "2022-05-23T20:26:51.725042Z", "completed_at": "2022-05-23T20:26:51.728100Z"}, {"name": "execute", "started_at": "2022-05-23T20:26:51.728484Z", "completed_at": "2022-05-23T20:26:51.728493Z"}], "thread_id": "Thread-2", "execution_time": 0.004591703414916992, "adapter_response": {}, "message": null, "failures": null, "unique_id": "model.basedosdados.mes_categoria_brasil_ipca"}, {"status": "success", "timing": [{"name": "compile", "started_at": "2022-05-23T20:26:51.731398Z", "completed_at": "2022-05-23T20:26:51.734152Z"}, {"name": "execute", "started_at": "2022-05-23T20:26:51.734542Z", "completed_at": "2022-05-23T20:26:51.734551Z"}], "thread_id": "Thread-2", "execution_time": 0.005022287368774414, "adapter_response": {}, "message": null, "failures": null, "unique_id": "model.basedosdados.mes_categoria_brasil_ipca15"}, {"status": "success", "timing": [{"name": "compile", "started_at": "2022-05-23T20:26:51.712276Z", "completed_at": "2022-05-23T20:26:51.755951Z"}, {"name": "execute", "started_at": "2022-05-23T20:26:51.759817Z", "completed_at": "2022-05-23T20:26:51.759829Z"}], "thread_id": "Thread-1", "execution_time": 0.048827171325683594, "adapter_response": {}, "message": null, "failures": null, "unique_id": "model.basedosdados.mes_brasil_ipca"}, {"status": "success", "timing": [{"name": "compile", "started_at": "2022-05-23T20:26:51.738770Z", "completed_at": "2022-05-23T20:26:51.761828Z"}, {"name": "execute", "started_at": "2022-05-23T20:26:51.762391Z", "completed_at": "2022-05-23T20:26:51.762400Z"}], "thread_id": "Thread-2", "execution_time": 0.026242494583129883, "adapter_response": {}, "message": null, "failures": null, "unique_id": "model.basedosdados.mes_categoria_municipio_inpc"}, {"status": "success", "timing": [{"name": "compile", "started_at": "2022-05-23T20:26:51.762122Z", "completed_at": "2022-05-23T20:26:51.765966Z"}, {"name": "execute", "started_at": "2022-05-23T20:26:51.767795Z", "completed_at": "2022-05-23T20:26:51.767808Z"}], "thread_id": "Thread-1", "execution_time": 0.007203817367553711, "adapter_response": {}, "message": null, "failures": null, "unique_id": "model.basedosdados.mes_categoria_municipio_ipca"}, {"status": "success", "timing": [{"name": "compile", "started_at": "2022-05-23T20:26:51.765696Z", "completed_at": "2022-05-23T20:26:51.769221Z"}, {"name": "execute", "started_at": "2022-05-23T20:26:51.770079Z", "completed_at": "2022-05-23T20:26:51.770088Z"}], "thread_id": "Thread-2", "execution_time": 0.00550389289855957, "adapter_response": {}, "message": null, "failures": null, "unique_id": "model.basedosdados.mes_categoria_municipio_ipca15"}, {"status": "success", "timing": [{"name": "compile", "started_at": "2022-05-23T20:26:51.770369Z", "completed_at": "2022-05-23T20:26:51.774480Z"}, {"name": "execute", "started_at": "2022-05-23T20:26:51.776155Z", "completed_at": "2022-05-23T20:26:51.776167Z"}], "thread_id": "Thread-1", "execution_time": 0.007165193557739258, "adapter_response": {}, "message": null, "failures": null, "unique_id": "model.basedosdados.mes_categoria_rm_inpc"}, {"status": "success", "timing": [{"name": "compile", "started_at": "2022-05-23T20:26:51.774183Z", "completed_at": "2022-05-23T20:26:51.778289Z"}, {"name": "execute", "started_at": "2022-05-23T20:26:51.780170Z", "completed_at": "2022-05-23T20:26:51.780179Z"}], "thread_id": "Thread-2", "execution_time": 0.007054567337036133, "adapter_response": {}, "message": null, "failures": null, "unique_id": "model.basedosdados.mes_categoria_rm_ipca"}, {"status": "success", "timing": [{"name": "compile", "started_at": "2022-05-23T20:26:51.782355Z", "completed_at": "2022-05-23T20:26:51.784627Z"}, {"name": "execute", "started_at": "2022-05-23T20:26:51.784952Z", "completed_at": "2022-05-23T20:26:51.784962Z"}], "thread_id": "Thread-2", "execution_time": 0.0035037994384765625, "adapter_response": {}, "message": null, "failures": null, "unique_id": "model.basedosdados.microdados"}, {"status": "success", "timing": [{"name": "compile", "started_at": "2022-05-23T20:26:51.778066Z", "completed_at": "2022-05-23T20:26:51.786398Z"}, {"name": "execute", "started_at": "2022-05-23T20:26:51.786980Z", "completed_at": "2022-05-23T20:26:51.786988Z"}], "thread_id": "Thread-1", "execution_time": 0.012544870376586914, "adapter_response": {}, "message": null, "failures": null, "unique_id": "model.basedosdados.mes_categoria_rm_ipca15"}, {"status": "success", "timing": [{"name": "compile", "started_at": "2022-05-23T20:26:51.791491Z", "completed_at": "2022-05-23T20:26:51.793378Z"}, {"name": "execute", "started_at": "2022-05-23T20:26:51.793640Z", "completed_at": "2022-05-23T20:26:51.793649Z"}], "thread_id": "Thread-1", "execution_time": 0.0032224655151367188, "adapter_response": {}, "message": null, "failures": null, "unique_id": "model.basedosdados.pessoa_fisica"}, {"status": "success", "timing": [{"name": "compile", "started_at": "2022-05-23T20:26:51.786684Z", "completed_at": "2022-05-23T20:26:51.796959Z"}, {"name": "execute", "started_at": "2022-05-23T20:26:51.797455Z", "completed_at": "2022-05-23T20:26:51.797463Z"}], "thread_id": "Thread-2", "execution_time": 0.011871576309204102, "adapter_response": {}, "message": null, "failures": null, "unique_id": "model.basedosdados.my_first_dbt_model"}, {"status": "success", "timing": [{"name": "compile", "started_at": "2022-05-23T20:26:51.795024Z", "completed_at": "2022-05-23T20:26:51.801221Z"}, {"name": "execute", "started_at": "2022-05-23T20:26:51.801990Z", "completed_at": "2022-05-23T20:26:51.801998Z"}], "thread_id": "Thread-1", "execution_time": 0.008080244064331055, "adapter_response": {}, "message": null, "failures": null, "unique_id": "model.basedosdados.pessoa_juridica"}, {"status": "success", "timing": [{"name": "compile", "started_at": "2022-05-23T20:26:51.799017Z", "completed_at": "2022-05-23T20:26:51.801625Z"}, {"name": "execute", "started_at": "2022-05-23T20:26:51.802268Z", "completed_at": "2022-05-23T20:26:51.802277Z"}], "thread_id": "Thread-2", "execution_time": 0.004762411117553711, "adapter_response": {}, "message": null, "failures": null, "unique_id": "model.basedosdados.responsavel"}, {"status": "success", "timing": [{"name": "compile", "started_at": "2022-05-23T20:26:51.805528Z", "completed_at": "2022-05-23T20:26:51.809542Z"}, {"name": "execute", "started_at": "2022-05-23T20:26:51.810156Z", "completed_at": "2022-05-23T20:26:51.810165Z"}], "thread_id": "Thread-1", "execution_time": 0.00653529167175293, "adapter_response": {}, "message": null, "failures": null, "unique_id": "model.basedosdados.terceirizados"}, {"status": "success", "timing": [{"name": "compile", "started_at": "2022-05-23T20:26:51.805878Z", "completed_at": "2022-05-23T20:26:51.809889Z"}, {"name": "execute", "started_at": "2022-05-23T20:26:51.810438Z", "completed_at": "2022-05-23T20:26:51.810446Z"}], "thread_id": "Thread-2", "execution_time": 0.006295919418334961, "adapter_response": {}, "message": null, "failures": null, "unique_id": "model.basedosdados.twitter_metrics"}, {"status": "success", "timing": [{"name": "compile", "started_at": "2022-05-23T20:26:51.813698Z", "completed_at": "2022-05-23T20:26:51.819621Z"}, {"name": "execute", "started_at": "2022-05-23T20:26:51.820102Z", "completed_at": "2022-05-23T20:26:51.820113Z"}], "thread_id": "Thread-1", "execution_time": 0.008393049240112305, "adapter_response": {}, "message": null, "failures": null, "unique_id": "model.basedosdados.twitter_metrics_agg"}, {"status": "success", "timing": [{"name": "compile", "started_at": "2022-05-23T20:26:51.813977Z", "completed_at": "2022-05-23T20:26:51.820443Z"}, {"name": "execute", "started_at": "2022-05-23T20:26:51.821660Z", "completed_at": "2022-05-23T20:26:51.821756Z"}], "thread_id": "Thread-2", "execution_time": 0.009369134902954102, "adapter_response": {}, "message": null, "failures": null, "unique_id": "model.basedosdados.my_second_dbt_model"}, {"status": "success", "timing": [{"name": "compile", "started_at": "2022-05-23T20:26:51.825818Z", "completed_at": "2022-05-23T20:26:51.848420Z"}, {"name": "execute", "started_at": "2022-05-23T20:26:51.849227Z", "completed_at": "2022-05-23T20:26:51.849240Z"}], "thread_id": "Thread-1", "execution_time": 0.02591848373413086, "adapter_response": {}, "message": null, "failures": null, "unique_id": "test.basedosdados.not_null_my_second_dbt_model_id.151b76d778"}, {"status": "success", "timing": [{"name": "compile", "started_at": "2022-05-23T20:26:51.826224Z", "completed_at": "2022-05-23T20:26:51.848772Z"}, {"name": "execute", "started_at": "2022-05-23T20:26:51.849646Z", "completed_at": "2022-05-23T20:26:51.849656Z"}], "thread_id": "Thread-2", "execution_time": 0.02577519416809082, "adapter_response": {}, "message": null, "failures": null, "unique_id": "test.basedosdados.unique_my_second_dbt_model_id.57a0f8c493"}], "elapsed_time": 1.5730645656585693, "args": {"log_format": "default", "write_json": true, "use_experimental_parser": false, "profiles_dir": "/home/runner/work/queries/queries", "use_cache": true, "compile": true, "version_check": true, "which": "generate", "rpc_method": "docs.generate"}}